esologs/__init__.py
esologs/async_base_client.py
esologs/auth.py
esologs/base_model.py
esologs/client.py
esologs/enums.py
esologs/exceptions.py
esologs/get_abilities.py
esologs/get_ability.py
esologs/get_character_by_id.py
esologs/get_character_encounter_ranking.py
esologs/get_character_encounter_rankings.py
esologs/get_character_reports.py
esologs/get_character_zone_rankings.py
esologs/get_class.py
esologs/get_classes.py
esologs/get_encounters_by_zone.py
esologs/get_factions.py
esologs/get_guild_by_id.py
esologs/get_item.py
esologs/get_item_set.py
esologs/get_item_sets.py
esologs/get_items.py
esologs/get_map.py
esologs/get_maps.py
esologs/get_npc.py
esologs/get_npcs.py
esologs/get_rate_limit_data.py
esologs/get_regions.py
esologs/get_report_by_code.py
esologs/get_report_events.py
esologs/get_report_graph.py
esologs/get_report_player_details.py
esologs/get_report_rankings.py
esologs/get_report_table.py
esologs/get_reports.py
esologs/get_world_data.py
esologs/get_zones.py
esologs/input_types.py
esologs/py.typed
esologs/validators.py
esologs_python-0.2.0a2.dist-info/licenses/LICENSE
esologs_python-0.2.0a2.dist-info/METADATA
esologs_python-0.2.0a2.dist-info/WHEEL
esologs_python-0.2.0a2.dist-info/top_level.txt
esologs_python-0.2.0a2.dist-info/RECORD
