Metadata-Version: 2.4
Name: esologs-python
Version: 0.2.0a2
Summary: A Python client library for the ESO Logs API v2
Author: Nick Knowles
License: MIT
Project-URL: Homepage, https://github.com/knowlen/esologs-python
Project-URL: Repository, https://github.com/knowlen/esologs-python
Project-URL: Issues, https://github.com/knowlen/esologs-python/issues
Project-URL: Documentation, https://esologs-python.readthedocs.io/
Project-URL: Changelog, https://github.com/knowlen/esologs-python/wiki/Changelog
Project-URL: Wiki, https://github.com/knowlen/esologs-python/wiki
Keywords: eso,elder-scrolls-online,esologs,api,graphql,combat-logs,mmorpg,gaming,api-client,python
Classifier: Development Status :: 3 - Alpha
Classifier: Intended Audience :: Developers
Classifier: License :: OSI Approved :: MIT License
Classifier: Operating System :: OS Independent
Classifier: Programming Language :: Python :: 3
Classifier: Programming Language :: Python :: 3.8
Classifier: Programming Language :: Python :: 3.9
Classifier: Programming Language :: Python :: 3.10
Classifier: Programming Language :: Python :: 3.11
Classifier: Programming Language :: Python :: 3.12
Classifier: Topic :: Games/Entertainment
Classifier: Topic :: Software Development :: Libraries :: Python Modules
Requires-Python: >=3.8
License-File: LICENSE
Requires-Dist: requests>=2.25.0
Requires-Dist: ariadne-codegen>=0.6.0
Requires-Dist: pydantic>=2.0.0
Requires-Dist: httpx>=0.24.0
Provides-Extra: dev
Requires-Dist: pytest>=6.0.0; extra == "dev"
Requires-Dist: pytest-asyncio>=0.21.0; extra == "dev"
Requires-Dist: pytest-cov>=4.0.0; extra == "dev"
Requires-Dist: pytest-timeout>=2.0.0; extra == "dev"
Requires-Dist: black>=22.0.0; extra == "dev"
Requires-Dist: isort>=5.0.0; extra == "dev"
Requires-Dist: ruff>=0.1.0; extra == "dev"
Requires-Dist: mypy>=1.0.0; extra == "dev"
Requires-Dist: pre-commit>=2.0.0; extra == "dev"
Requires-Dist: types-requests>=2.25.0; extra == "dev"
Provides-Extra: websockets
Requires-Dist: websockets>=11.0.0; extra == "websockets"
Provides-Extra: pandas
Requires-Dist: pandas>=1.3.0; extra == "pandas"
Provides-Extra: docs
Requires-Dist: mkdocs>=1.5.0; extra == "docs"
Requires-Dist: mkdocs-material>=9.4.0; extra == "docs"
Requires-Dist: mkdocs-minify-plugin>=0.7.0; extra == "docs"
Requires-Dist: mkdocs-git-revision-date-localized-plugin>=1.2.0; extra == "docs"
Requires-Dist: pymdown-extensions>=10.0.0; extra == "docs"
Provides-Extra: all
Requires-Dist: esologs-python[dev,docs,pandas,websockets]; extra == "all"
Dynamic: license-file
